{
    "nodes": [
        {
            "id": "4_9",
            "articles": [
                "24347"
            ],
            "label": "Budget has its work cut out",
            "publisher": "The Australian Financial Review",
            "node_words": "tax, income, marginal, tax rates, rate, marginal tax, cuts, earners, income earners, rates",
            "time": "1999-11-03",
            "is_hidden": 0
        },
        {
            "id": "0_1",
            "articles": [
                "30890",
                "2524",
                "27643",
                "13894",
                "30881",
                "14032"
            ],
            "label": "\n200,000 WILL BE HIT BY CUTS IN RENT SUBSIDIES\n",
            "publisher": " Sydney Morning Herald ",
            "node_words": "housing, rent, public, public housing, assistance, rent assistance, government, week, ops, private",
            "time": "1986-10-14",
            "is_hidden": 0
        },
        {
            "id": "1_3",
            "articles": [
                "27018"
            ],
            "label": "\nTHE GREAT DIVIDE\n",
            "publisher": " Sydney Morning Herald ",
            "node_words": "divorce, children, marriages, marriage, parents, cent, relationship, separation, years, family",
            "time": "1992-09-17",
            "is_hidden": 0
        },
        {
            "id": "5_6",
            "articles": [
                "12237"
            ],
            "label": "Carers must be given fair support",
            "publisher": "Herald-Sun",
            "node_words": "father, home, security, tax, social security, mother, son, old, time, social",
            "time": "2008-12-12",
            "is_hidden": 0
        },
        {
            "id": "3_9",
            "articles": [
                "22211",
                "9694"
            ],
            "label": "\nTax: Does Labor Have A Credible Alternative?\n",
            "publisher": " The Age ",
            "node_words": "tax, family, income, family tax, families, rebate, package, 000, assistance, cent",
            "time": "1998-05-23",
            "is_hidden": 0
        },
        {
            "id": "2_4",
            "articles": [
                "22533",
                "21691",
                "9292",
                "12748"
            ],
            "label": "\nMother LOAD.\n",
            "publisher": "The Australian",
            "node_words": "women, single, mothers, domestic, violence, work, single mothers, domestic violence, time, man",
            "time": "1996-06-27",
            "is_hidden": 0
        },
        {
            "id": "2_9",
            "articles": [
                "4026",
                "4001",
                "25936"
            ],
            "label": "\nDOWNWARD ENVY / WHY MIDDLE AUSTRALIA HATES THE POOR.\n",
            "publisher": "The Australian",
            "node_words": "tax, men, magazine, max, income, magazines, ralph, rebate, men health, health",
            "time": "1996-06-27",
            "is_hidden": 0
        },
        {
            "id": "1_7",
            "articles": [
                "29159",
                "30710"
            ],
            "label": "\nA Time When Income Inequality Doesn't Really Matter\n",
            "publisher": " The Age ",
            "node_words": "welfare, safety net, safety, net, social, people, basic income, social welfare, basic, economic",
            "time": "1992-09-17",
            "is_hidden": 0
        },
        {
            "id": "1_5",
            "articles": [
                "18600"
            ],
            "label": "\nJobs Help To Boost Incomes On Welfare\n",
            "publisher": " The Age ",
            "node_words": "unemployed, people, unemployment, term, long, work, long term, unemployed people, job, term unemployed",
            "time": "1992-09-17",
            "is_hidden": 0
        },
        {
            "id": "2_8",
            "articles": [
                "7241",
                "7244",
                "10617"
            ],
            "label": "\nPoorer Families Get Some Tax Relief\n",
            "publisher": " Sydney Morning Herald ",
            "node_words": "care, centres, child, child care, childcare, community, day care, fees, care centres, 000",
            "time": "1996-06-27",
            "is_hidden": 0
        },
        {
            "id": "0_2",
            "articles": [
                "11510",
                "16763"
            ],
            "label": "\nMORE AND MORE SOLO MOTHERS IN POVERTY\n",
            "publisher": " Sydney Morning Herald ",
            "node_words": "poverty, cent, children, families, sole, 000, number, parents, parent, living poverty",
            "time": "1986-10-14",
            "is_hidden": 0
        },
        {
            "id": "3_8",
            "articles": [
                "16607",
                "15045"
            ],
            "label": "Kids Pay Ground",
            "publisher": "Sydney Morning Herald",
            "node_words": "care, child, child care, centres, care assistance, fees, assistance, children, rebate, government",
            "time": "1998-05-23",
            "is_hidden": 0
        },
        {
            "id": "2_0",
            "articles": [
                "27794"
            ],
            "label": "\nBALANCING ACT\n",
            "publisher": " Sydney Morning Herald ",
            "node_words": "newman, minister, senator, newman said, security minister, social security, security, report, senator newman, social",
            "time": "1996-06-27",
            "is_hidden": 0
        },
        {
            "id": "3_0",
            "articles": [
                "15890"
            ],
            "label": "\nCensure for Newman over reform paper.\n",
            "publisher": "Hobart Mercury",
            "node_words": "newman, senator, senator newman, paper, welfare, minister, discussion, discussion paper, said, speech",
            "time": "1998-05-23",
            "is_hidden": 0
        },
        {
            "id": "5_4",
            "articles": [
                "32263"
            ],
            "label": "Liberal Party lost the trust of Australian women long before Morrison",
            "publisher": "The Sydney Morning Herald - Online",
            "node_words": "women, morrison, party, violence, gender, men, work, mothers, government, time",
            "time": "2008-12-12",
            "is_hidden": 0
        },
        {
            "id": "3_7",
            "articles": [
                "26904",
                "6743",
                "15913"
            ],
            "label": "\nWelfare in US not quite what it seems.\n",
            "publisher": "The Australian",
            "node_words": "welfare, reform, people, welfare reform, government, net, need, safety net, safety, term",
            "time": "1998-05-23",
            "is_hidden": 0
        },
        {
            "id": "1_9",
            "articles": [
                "20320"
            ],
            "label": "\nGAP GROWING? KEATING SAYS NO\n",
            "publisher": " Sydney Morning Herald ",
            "node_words": "tax, spouse, income, rebate, spouse rebate, taxes, dependent spouse, cent, dependent, families",
            "time": "1992-09-17",
            "is_hidden": 0
        },
        {
            "id": "2_7",
            "articles": [
                "5242"
            ],
            "label": "Dismantling the welfare state",
            "publisher": "The Australian Financial Review",
            "node_words": "welfare, welfare state, state, social, people, social welfare, society, social services, dependency, dependence",
            "time": "1996-06-27",
            "is_hidden": 1
        },
        {
            "id": "2_5",
            "articles": [
                "4346",
                "11747",
                "22258"
            ],
            "label": "\nWORKPLACE UPDATE.\n",
            "publisher": "Herald-Sun",
            "node_words": "sex, prostitution, men, women, sexual, unemployed, prostitutes, work, job, says",
            "time": "1996-06-27",
            "is_hidden": 0
        },
        {
            "id": "0_3",
            "articles": [
                "7463"
            ],
            "label": "\nFOR THE KIDS, SEPARATED PARENTS CAN MEAN RICHES TO RAGS\n",
            "publisher": " Sydney Morning Herald ",
            "node_words": "aifs, divorce, marriage, australian, cent, report australian, marriages, fall poverty, australian institute, 1986",
            "time": "1986-10-14",
            "is_hidden": 1
        },
        {
            "id": "3_3",
            "articles": [
                "26605",
                "3933"
            ],
            "label": "\nDIVORCE NOT SO BAD FOR CHILDREN.\n",
            "publisher": "Daily Telegraph",
            "node_words": "divorce, children, research, schooling, marriage, parents, marriages, people, education, educational",
            "time": "1998-05-23",
            "is_hidden": 0
        },
        {
            "id": "5_3",
            "articles": [
                "2314"
            ],
            "label": "Is there ever a good divorce?",
            "publisher": "The Sydney Morning Herald",
            "node_words": "children, divorce, marriage, parents, divorces, couples, married, good divorce, conflict, good",
            "time": "2008-12-12",
            "is_hidden": 0
        },
        {
            "id": "0_5",
            "articles": [
                "28322",
                "23818"
            ],
            "label": "\nTHE TIMETABLE FOR CHANGE\n",
            "publisher": " Sydney Morning Herald ",
            "node_words": "unemployed, benefits, term, work, unemployment, term unemployed, long term, unemployment benefits, long, employment",
            "time": "1986-10-14",
            "is_hidden": 0
        },
        {
            "id": "1_1",
            "articles": [
                "8840",
                "2524"
            ],
            "label": "POLITICS STILL DRIVES HOME OWNERSHIP",
            "publisher": "The Australian Financial Review",
            "node_words": "housing, public, public housing, rent, assistance, private, rent assistance, people, government, rental",
            "time": "1992-09-17",
            "is_hidden": 0
        },
        {
            "id": "4_3",
            "articles": [
                "1479"
            ],
            "label": "Double Or Nothing",
            "publisher": "Sydney Morning Herald",
            "node_words": "marriage, facto, divorce, relationship, relationships, children, couples, married, maushart, parents",
            "time": "1999-11-03",
            "is_hidden": 0
        },
        {
            "id": "0_7",
            "articles": [
                "4746"
            ],
            "label": "\nUNAPPEALING PHILOSOPHY FOR WOMEN\n",
            "publisher": " Sydney Morning Herald ",
            "node_words": "rooney, welfare, cbs, advocate, social, safety, social welfare, lobby, safety net, state",
            "time": "1986-10-14",
            "is_hidden": 0
        },
        {
            "id": "2_2",
            "articles": [
                "23656"
            ],
            "label": "\nBreak-ups `the Main Cause Of Poverty'\n",
            "publisher": " Sydney Morning Herald ",
            "node_words": "families, cent, children, parent, sole, poverty, poor, poor families, lone, parent families",
            "time": "1996-06-27",
            "is_hidden": 1
        },
        {
            "id": "3_6",
            "articles": [
                "15758"
            ],
            "label": "\nSlugging victims a second time.\n",
            "publisher": "Courier Mail",
            "node_words": "social, social security, security, jaidyn, son, mother, years, alison, said, children",
            "time": "1998-05-23",
            "is_hidden": 1
        },
        {
            "id": "3_2",
            "articles": [
                "14848",
                "25086",
                "30238",
                "11371",
                "11376",
                "18379",
                "19509"
            ],
            "label": "By 1996, Fewer Lived In Poverty",
            "publisher": "The Age",
            "node_words": "families, children, cent, parent, poverty, parent families, living, parents, sole, dependent",
            "time": "1998-05-23",
            "is_hidden": 0
        },
        {
            "id": "1_4",
            "articles": [
                "25614"
            ],
            "label": "\nEncouraging Women To Explore Job Options\n",
            "publisher": " The Age ",
            "node_words": "women, wel, says, work, mothers, men, issues, workforce, time, new",
            "time": "1992-09-17",
            "is_hidden": 0
        },
        {
            "id": "0_8",
            "articles": [
                "2701",
                "21110",
                "22274"
            ],
            "label": "PUBLIC OR PRIVATE, NO MAGIC WAND WILL END THE PROBLEM OF CHILD CARE",
            "publisher": "The Australian Financial Review",
            "node_words": "care, child care, child, places, government, centres, fee, 000, fee relief, relief",
            "time": "1986-10-14",
            "is_hidden": 0
        },
        {
            "id": "1_8",
            "articles": [
                "25507"
            ],
            "label": "\nWelfare Feels The Pain\n",
            "publisher": " The Age ",
            "node_words": "care, child, child care, children, million, government, mr john, services, said, mr",
            "time": "1992-09-17",
            "is_hidden": 1
        },
        {
            "id": "1_6",
            "articles": [
                "28946",
                "28931",
                "11915",
                "23791",
                "17244",
                "17243"
            ],
            "label": "\nFoster Love & Care\n",
            "publisher": " The Age ",
            "node_words": "security, social security, social, mother, children, old, family, said, time, home",
            "time": "1992-09-17",
            "is_hidden": 0
        },
        {
            "id": "4_2",
            "articles": [
                "9972"
            ],
            "label": "The Politics Of Appeasing The Poor",
            "publisher": "Sydney Morning Herald",
            "node_words": "families, children, poverty, parents, single, cent, australia, parent, mothers, sole",
            "time": "1999-11-03",
            "is_hidden": 1
        },
        {
            "id": "3_4",
            "articles": [
                "12154"
            ],
            "label": "\nQuest for equality is still germane.\n",
            "publisher": "Courier Mail",
            "node_words": "women, single, mothers, men, single mothers, violence, working, time, domestic, work",
            "time": "1998-05-23",
            "is_hidden": 0
        },
        {
            "id": "5_2",
            "articles": [
                "8006"
            ],
            "label": "Taking sides over shacking up",
            "publisher": "The Sydney Morning Herald",
            "node_words": "cent, parents, families, single, children, sole, poverty, sole parents, australia, parent",
            "time": "2008-12-12",
            "is_hidden": 1
        },
        {
            "id": "0_0",
            "articles": [
                "17135"
            ],
            "label": "\nHAWKE NEEDS MORE OF A SWAN SONG\n",
            "publisher": " Sydney Morning Herald ",
            "node_words": "mr, application, details, new, department, yesterday, report, announce details, graham, issued discussion",
            "time": "1986-10-14",
            "is_hidden": 1
        },
        {
            "id": "0_9",
            "articles": [
                "27612"
            ],
            "label": "\nHOWE DOWNPLAYS SPENDING CUTS\n",
            "publisher": " Sydney Morning Herald ",
            "node_words": "tax, rebate, income, spouse, parent, sole, child, 000, cent, families",
            "time": "1986-10-14",
            "is_hidden": 0
        },
        {
            "id": "1_0",
            "articles": [
                "21810"
            ],
            "label": "\nCommunity Groups Call For Talks On Policies\n",
            "publisher": " The Age ",
            "node_words": "senator, newman, said, senator bell, bell, government, consultation, coalition, yesterday, cabinet",
            "time": "1992-09-17",
            "is_hidden": 1
        },
        {
            "id": "5_9",
            "articles": [
                "10920",
                "17406"
            ],
            "label": "Letters",
            "publisher": "The Sydney Morning Herald",
            "node_words": "tax, income, lito, government, income tax, taxes, adult children, adult, low, australia",
            "time": "2008-12-12",
            "is_hidden": 0
        },
        {
            "id": "4_0",
            "articles": [
                "13030",
                "30251",
                "995",
                "19019",
                "13049",
                "1075",
                "25339",
                "9991"
            ],
            "label": "Cabinet Approves Reining In Welfare",
            "publisher": "Sydney Morning Herald",
            "node_words": "newman, senator, senator newman, welfare, minister, paper, jocelyn, jocelyn newman, community services, family community",
            "time": "1999-11-03",
            "is_hidden": 0
        },
        {
            "id": "4_8",
            "articles": [
                "858",
                "15045"
            ],
            "label": "Who Cares?",
            "publisher": "The Age",
            "node_words": "2001, childcare centres, community childcare, childcare, care, child, hour, past years, child care, 1996",
            "time": "1999-11-03",
            "is_hidden": 0
        },
        {
            "id": "1_2",
            "articles": [
                "30585"
            ],
            "label": "\nWHY THE WELFARE SYSTEM IS COMING UNSTUCK\n",
            "publisher": " Sydney Morning Herald ",
            "node_words": "cent, families, poverty, sole, parent, children, parents, parent families, sole parents, single",
            "time": "1992-09-17",
            "is_hidden": 0
        },
        {
            "id": "0_4",
            "articles": [
                "11711",
                "5023"
            ],
            "label": "COALITION WINNING FEMALE VOTERS WITH REBATE PLAN",
            "publisher": "The Australian Financial Review",
            "node_words": "women, question, cent, mothers, government, party, voters, pension, group, said",
            "time": "1986-10-14",
            "is_hidden": 0
        },
        {
            "id": "0_6",
            "articles": [
                "520"
            ],
            "label": "\nSearching For The Lost Families\n",
            "publisher": " The Age ",
            "node_words": "social security, security, social, said, bettina cass, fitzgerald, cass, family, bettina, sister",
            "time": "1986-10-14",
            "is_hidden": 1
        },
        {
            "id": "4_7",
            "articles": [
                "8275",
                "9661",
                "30162"
            ],
            "label": "\nOne in four on benefits.\n",
            "publisher": "Daily Telegraph",
            "node_words": "welfare, reform, government, welfare reform, recipients, welfare recipients, people, work, safety net, net",
            "time": "1999-11-03",
            "is_hidden": 0
        },
        {
            "id": "5_8",
            "articles": [
                "24693"
            ],
            "label": "Childcare is a middle-class perk",
            "publisher": "The Australian Financial Review",
            "node_words": "childcare, mothers, parents, children, particularly, child, better, melbourne, month old, days",
            "time": "2008-12-12",
            "is_hidden": 0
        },
        {
            "id": "4_6",
            "articles": [
                "24185",
                "24187"
            ],
            "label": "Taking the scalpel to DOCS",
            "publisher": "The Sydney Morning Herald",
            "node_words": "social security, security, social, security recipients, people, recipients, marg, years, left, actually",
            "time": "1999-11-03",
            "is_hidden": 0
        },
        {
            "id": "5_7",
            "articles": [
                "20728"
            ],
            "label": "Living off the public teat",
            "publisher": "The Sydney Morning Herald",
            "node_words": "welfare, people, welfare recipients, services, recipients, dependency, welfare dependency, welfare state, government, social",
            "time": "2008-12-12",
            "is_hidden": 0
        },
        {
            "id": "4_4",
            "articles": [
                "13135"
            ],
            "label": "Home And A Wage",
            "publisher": "Sydney Morning Herald",
            "node_words": "women, mothers, single, men, single mothers, work, just, equality, children, workforce",
            "time": "1999-11-03",
            "is_hidden": 0
        },
        {
            "id": "2_3",
            "articles": [
                "23819",
                "23830",
                "23890",
                "19301",
                "18756"
            ],
            "label": "\nWHY MARRIAGE MATTERS / Fault must be found for just family law.\n",
            "publisher": "The Australian",
            "node_words": "divorce, children, marriage, parents, conflict, relationships, marriages, divorced, research, family",
            "time": "1996-06-27",
            "is_hidden": 0
        },
        {
            "id": "2_6",
            "articles": [
                "15999"
            ],
            "label": "\nSecrets and truths.\n",
            "publisher": "The Australian",
            "node_words": "social, social security, mother, security, father, moved, home, mum, rebecca, said",
            "time": "1996-06-27",
            "is_hidden": 0
        },
        {
            "id": "2_1",
            "articles": [
                "25950"
            ],
            "label": "\nDOWNWARD ENVY / WHY MIDDLE AUSTRALIA HATES THE POOR.\n",
            "publisher": "The Australian",
            "node_words": "housing, caravan, 000, home, public housing, park, public, rental, caravans, residents",
            "time": "1996-06-27",
            "is_hidden": 0
        }
    ],
    "links": [
        {
            "source": "0_2",
            "target": "1_2",
            "line_id": "0"
        },
        {
            "source": "1_2",
            "target": "2_2",
            "line_id": "0"
        },
        {
            "source": "2_2",
            "target": "3_2",
            "line_id": "0"
        },
        {
            "source": "3_2",
            "target": "4_2",
            "line_id": "0"
        },
        {
            "source": "4_2",
            "target": "5_2",
            "line_id": "0"
        },
        {
            "source": "0_4",
            "target": "1_4",
            "line_id": "1"
        },
        {
            "source": "1_4",
            "target": "2_4",
            "line_id": "1"
        },
        {
            "source": "2_4",
            "target": "3_4",
            "line_id": "1"
        },
        {
            "source": "3_4",
            "target": "4_4",
            "line_id": "1"
        },
        {
            "source": "4_4",
            "target": "5_4",
            "line_id": "1"
        },
        {
            "source": "0_9",
            "target": "1_9",
            "line_id": "2"
        },
        {
            "source": "1_9",
            "target": "2_9",
            "line_id": "2"
        },
        {
            "source": "2_9",
            "target": "3_9",
            "line_id": "2"
        },
        {
            "source": "3_9",
            "target": "4_9",
            "line_id": "2"
        },
        {
            "source": "4_9",
            "target": "5_9",
            "line_id": "2"
        },
        {
            "source": "0_1",
            "target": "1_1",
            "line_id": "3"
        },
        {
            "source": "1_1",
            "target": "2_1",
            "line_id": "3"
        },
        {
            "source": "2_1",
            "target": "3_9",
            "line_id": "3"
        },
        {
            "source": "3_9",
            "target": "4_9",
            "line_id": "3"
        },
        {
            "source": "4_9",
            "target": "5_9",
            "line_id": "3"
        },
        {
            "source": "0_7",
            "target": "1_7",
            "line_id": "4"
        },
        {
            "source": "1_7",
            "target": "2_7",
            "line_id": "4"
        },
        {
            "source": "2_7",
            "target": "3_7",
            "line_id": "4"
        },
        {
            "source": "3_7",
            "target": "4_7",
            "line_id": "4"
        },
        {
            "source": "4_7",
            "target": "5_7",
            "line_id": "4"
        },
        {
            "source": "0_5",
            "target": "1_5",
            "line_id": "5"
        },
        {
            "source": "1_5",
            "target": "2_5",
            "line_id": "5"
        },
        {
            "source": "2_5",
            "target": "3_4",
            "line_id": "5"
        },
        {
            "source": "3_4",
            "target": "4_4",
            "line_id": "5"
        },
        {
            "source": "4_4",
            "target": "5_4",
            "line_id": "5"
        },
        {
            "source": "0_8",
            "target": "1_8",
            "line_id": "6"
        },
        {
            "source": "1_8",
            "target": "2_8",
            "line_id": "6"
        },
        {
            "source": "2_8",
            "target": "3_8",
            "line_id": "6"
        },
        {
            "source": "3_8",
            "target": "4_8",
            "line_id": "6"
        },
        {
            "source": "4_8",
            "target": "5_8",
            "line_id": "6"
        },
        {
            "source": "0_3",
            "target": "1_3",
            "line_id": "7"
        },
        {
            "source": "1_3",
            "target": "2_3",
            "line_id": "7"
        },
        {
            "source": "2_3",
            "target": "3_3",
            "line_id": "7"
        },
        {
            "source": "3_3",
            "target": "4_3",
            "line_id": "7"
        },
        {
            "source": "4_3",
            "target": "5_3",
            "line_id": "7"
        },
        {
            "source": "0_6",
            "target": "1_6",
            "line_id": "8"
        },
        {
            "source": "1_6",
            "target": "2_6",
            "line_id": "8"
        },
        {
            "source": "2_6",
            "target": "3_6",
            "line_id": "8"
        },
        {
            "source": "3_6",
            "target": "4_6",
            "line_id": "8"
        },
        {
            "source": "4_6",
            "target": "5_6",
            "line_id": "8"
        },
        {
            "source": "0_0",
            "target": "1_0",
            "line_id": "9"
        },
        {
            "source": "1_0",
            "target": "2_0",
            "line_id": "9"
        },
        {
            "source": "2_0",
            "target": "3_0",
            "line_id": "9"
        },
        {
            "source": "3_0",
            "target": "4_0",
            "line_id": "9"
        },
        {
            "source": "4_0",
            "target": "5_7",
            "line_id": "9"
        }
    ],
    "articles": [
        {
            "id": "11376",
            "publisher": "The Age",
            "title": "Children's Poverty To Worsen",
            "url": null,
            "timestamp": "1999-07-15",
            "text": "Professor Gregory also told the conference:\n\n* More than one in four dependent children live in a family where no male is employed, up from 16.2per cent 20 years ago. * The number of jobless families increased by 229,000 between 1989 and 1998. ..."
        },
        {
            "id": "7241",
            "publisher": " Sydney Morning Herald ",
            "title": "\nGIVE US A BREAK\n",
            "url": null,
            "timestamp": "1997-05-19",
            "text": "Since 1991, when the Labor Government extended child care subsidies to\nthe private sector, but installed no planning processes and no funding\ncaps, child-care centres sprang up like mushrooms after a storm. ..."
        },
        {
            "id": "21691",
            "publisher": " The Age ",
            "title": "\nBlaming Mothers Is No Way To Help The Family\n",
            "url": null,
            "timestamp": "1998-03-12",
            "text": "We remember the faces of tiny\nchildren in newspapers,  abused, beaten or killed because some women put\nhaving a man - any man - before  their children's welfare. Yet how\nunfair of us to assume that most, or even many, single mothers are like\nthis. ..."
        },
        {
            "id": "25339",
            "publisher": "The Age",
            "title": "Welfare's Swings And Roundabouts",
            "url": null,
            "timestamp": "2000-12-18",
            "text": "Senator Newman is expected to announce her retirement soon and this may be one reason why the government has embarked on the unorthodox course of releasing the outline without the fine print. ..."
        },
        {
            "id": "19301",
            "publisher": "The Australian",
            "title": "\nWHY MARRIAGE MATTERS / Fault must be found for just family law.\n",
            "url": null,
            "timestamp": "1996-09-21",
            "text": "Under present law, a spouse who wants to keep trying at a faltering marriage has no defence against a spouse who wants, unilaterally, to end it - perhaps for frivolous or dishonourable reasons. ..."
        },
        {
            "id": "30710",
            "publisher": " Sydney Morning Herald ",
            "title": "\nDealing With The Real Issues\n",
            "url": null,
            "timestamp": "1995-04-21",
            "text": "On this\nfoundation many academic careers and many high salaries were built, as\nwell  as a permanently dissatisfied welfare lobby. ..."
        },
        {
            "id": "25936",
            "publisher": "The Australian",
            "title": "\nDOWNWARD ENVY / WHY MIDDLE AUSTRALIA HATES THE POOR.\n",
            "url": null,
            "timestamp": "1996-11-02",
            "text": "You might think of the rich businessmen who can hide assets offshore and end up paying next to nothing in tax, and yes, something should be done about that. ..."
        },
        {
            "id": "28931",
            "publisher": " The Age ",
            "title": "\nHeartfelt Search For Ties That Bind Across Lost Years\n",
            "url": null,
            "timestamp": "1993-06-15",
            "text": "Three years ago, Mr Dynon and his two brothers learnt their mother had\nhad a baby girl when she was 17. ..."
        },
        {
            "id": "2524",
            "publisher": "The Australian Financial Review",
            "title": "POLITICS STILL DRIVES HOME OWNERSHIP",
            "url": null,
            "timestamp": "1992-09-17",
            "text": "Some of the funds currently dedicated to building public housing will be used to provide an interest rate subsidy to provide guaranteed market returns to the private sector companies which will contract to provide housing to government housing authorities ..."
        },
        {
            "id": "16763",
            "publisher": " Sydney Morning Herald ",
            "title": "\nMORE AND MORE SOLO MOTHERS IN POVERTY\n",
            "url": null,
            "timestamp": "1991-03-27",
            "text": "One of the study's authors, Dr Russell Ross, said the figures showed\nthat when sole mothers were in full-time employment for the whole year,\ntheir poverty  rate was well below that of the population as a whole. ..."
        },
        {
            "id": "15890",
            "publisher": "Hobart Mercury",
            "title": "\nCensure for Newman over reform paper.\n",
            "url": null,
            "timestamp": "1999-10-14",
            "text": "The Australian Democrats were supported by Labor and independents to censure Senator Newman by 34 to 29 votes. They also set Monday as another deadline for Senator Newman to table the paper. ..."
        },
        {
            "id": "12237",
            "publisher": "Herald-Sun",
            "title": "Carers must be given fair support",
            "url": null,
            "timestamp": "2011-02-02",
            "text": "What struck me about Rebecca's story was the fact that she had to give up her job to care for Nate and is now struggling financially. ..."
        },
        {
            "id": "17244",
            "publisher": " Sydney Morning Herald ",
            "title": "\nStolen Innocence\n",
            "url": null,
            "timestamp": "1996-04-03",
            "text": "She was in a bed somewhere, frozen with\nfear, screwing her eyes up tightly as a grown-up shadow moved towards\nher. ..."
        },
        {
            "id": "2314",
            "publisher": "The Sydney Morning Herald",
            "title": "Is there ever a good divorce?",
            "url": null,
            "timestamp": "2012-02-18",
            "text": "Divorce invariably involves conflict, even if minimal. Conflict between parents impacts adversely on children. The greater the conflict, the greater the impact. ..."
        },
        {
            "id": "25086",
            "publisher": "The Age",
            "title": "18% Of Young In Jobless Homes",
            "url": null,
            "timestamp": "1999-10-12",
            "text": "In couple families, the bureau reports, 270,000 children were living in homes where neither parent was working. ..."
        },
        {
            "id": "3933",
            "publisher": "Adelaide Advertiser",
            "title": "\nMother of all changes.\n",
            "url": null,
            "timestamp": "1998-07-11",
            "text": "The influence of religion and social pressures, two factors which used to persuade couples to stay together, are also waning. ..."
        },
        {
            "id": "4346",
            "publisher": " Sydney Morning Herald ",
            "title": "\nReversal Of Fortune Sees Help Go To The Better Off\n",
            "url": null,
            "timestamp": "1998-05-13",
            "text": "Now they will\nlose part of their benefit if they voluntarily seek jobs outside their\nlocal area, but subsequently refuse an offer. And there will be further crackdowns on unemployed people who move to\nareas of so-called lower employment opportunities. ..."
        },
        {
            "id": "30585",
            "publisher": " Sydney Morning Herald ",
            "title": "\nWHY THE WELFARE SYSTEM IS COMING UNSTUCK\n",
            "url": null,
            "timestamp": "1994-11-16",
            "text": "Poverty among single parents also rose from 41 per cent at the start\nof the decade to almost 48 per cent at its end. ..."
        },
        {
            "id": "11711",
            "publisher": " The Age ",
            "title": "\nWho Cares For Our Children?\n",
            "url": null,
            "timestamp": "1992-08-05",
            "text": "BUT in all the national surveys of child care, the cost of the service\nstill shows up as a major barrier for many women contemplating\nre-entering the workforce. ..."
        },
        {
            "id": "17243",
            "publisher": " Sydney Morning Herald ",
            "title": "\nStolen Innocence\n",
            "url": null,
            "timestamp": "1996-04-03",
            "text": "A memory\nshe had buried long ago was slowly awakening, a memory that made great\ngulping bubbles of grief and horror rise up out of her throat, and her\nhands go clammy. And then, there it was: this foul, horrifying image of\nherself as a five-year-old. ..."
        },
        {
            "id": "27794",
            "publisher": " Sydney Morning Herald ",
            "title": "\nBALANCING ACT\n",
            "url": null,
            "timestamp": "1998-05-20",
            "text": "There will be less\nfriction between parents, says Newman, \"and obviously that's of\nenormous importance to the well-being of children\". ..."
        },
        {
            "id": "8840",
            "publisher": " The Age ",
            "title": "\nDallas\n",
            "url": null,
            "timestamp": "1995-12-16",
            "text": "And, says Mr Button, ``essentially, governments are also locked into a\nfantasy that consumers of public housing will one day be able to afford\ntheir own home. That's just not a realistic expectation. ..."
        },
        {
            "id": "13030",
            "publisher": " The West Australian ",
            "title": "\nMinister Snubs Welfare Group On Payout Cut\n",
            "url": null,
            "timestamp": "2000-03-17",
            "text": "She dismissed the newspaper report as having no authority and said it\nwas inconsistent with what the reference group had told her. \"I think there was a suggestion that we were going to slash benefits,\"\nSenator Newman said. ..."
        },
        {
            "id": "4746",
            "publisher": " Sydney Morning Herald ",
            "title": "\nUNAPPEALING PHILOSOPHY FOR WOMEN\n",
            "url": null,
            "timestamp": "1989-07-05",
            "text": "It is wrong to see welfare as a luxury. Even where\ngovernments accept some responsibility, it is accepted with reluctance. ..."
        },
        {
            "id": "15999",
            "publisher": "The Australian",
            "title": "\nSecrets and truths.\n",
            "url": null,
            "timestamp": "1997-09-20",
            "text": "The parallel with her mother's protective code of secrecy is profound. \"My search for my own identity, I realised, had to take a back seat to the construction of my child's identity and sense of self-worth. My father's identity remained unknown. ..."
        },
        {
            "id": "30162",
            "publisher": "Daily Telegraph",
            "title": "\nOne in four on benefits.\n",
            "url": null,
            "timestamp": "2000-01-26",
            "text": "There was a decline until 1991 when welfare recipients rose again until they remained virtually steady by the mid-1990s. The greatest increases in dependence on welfare payments have been among working age people. ..."
        },
        {
            "id": "9991",
            "publisher": "Sydney Morning Herald",
            "title": "Slashing Welfare Not On Agenda, Says Newman",
            "url": null,
            "timestamp": "2000-03-16",
            "text": "Senator Newman was responding to a Herald article saying a Government-commissioned report would recommend that unemployment, sole parent and disabled benefits be rolled into one payment. ..."
        },
        {
            "id": "27018",
            "publisher": " Sydney Morning Herald ",
            "title": "\nTHE GREAT DIVIDE\n",
            "url": null,
            "timestamp": "1993-02-18",
            "text": "\"Marriage was the most common form of partnership by 1987, and most of\nthe  remarried had lived with their spouse before marriage.\" The study shows that most of those without an intimate relationship\nwished  they had one. ..."
        },
        {
            "id": "15913",
            "publisher": "The Australian",
            "title": "\nWelfare in US not quite what it seems.\n",
            "url": null,
            "timestamp": "1998-07-31",
            "text": "Welfare in US not quite what it seems. ..."
        },
        {
            "id": "18379",
            "publisher": "The Age",
            "title": "By 1996, Fewer Lived In Poverty",
            "url": null,
            "timestamp": "1999-02-12",
            "text": "``The key reason for this dramatic fall in child poverty was the sharp growth in government cash payments to low-income families with children.'' ..."
        },
        {
            "id": "12154",
            "publisher": "Courier Mail",
            "title": "\nQuest for equality is still germane.\n",
            "url": null,
            "timestamp": "1999-10-06",
            "text": "The history of Australian feminism over the past 100 years is a record of political achievement leading to major changes in the relations between the sexes. Women have succeeded in campaigns for fundamental political, civil and economic rights. ..."
        },
        {
            "id": "14032",
            "publisher": " Sydney Morning Herald ",
            "title": "\nHOUSING POLICY DEBATE PROVIDES FIRM GROUNDS FOR IDEOLOGICAL CLASH\n",
            "url": null,
            "timestamp": "1989-07-10",
            "text": "The upshot is that, under a joint Federal-State funding agreement\nwhich accounts for most government spending on housing, there will be a\nmajor expansion of the public housing program, with more than $1 billion\neach year. ..."
        },
        {
            "id": "24187",
            "publisher": "The Sydney Morning Herald",
            "title": "Taking the scalpel to DOCS",
            "url": null,
            "timestamp": "2008-07-19",
            "text": "Her children were clingy, and frightened when she was away. She is engaged with a Burnside family support service, and doing well.She is bewildered about why, when she sought help, she was not able to access it. ..."
        },
        {
            "id": "23818",
            "publisher": " Sydney Morning Herald ",
            "title": "\nTHE TIMETABLE FOR CHANGE\n",
            "url": null,
            "timestamp": "1987-06-23",
            "text": "Application of benefits income test on fortnightly basis. *Sickness benefit brought into line with unemployment benefit.*Subject to enactment of legislation. ..."
        },
        {
            "id": "13135",
            "publisher": "Sydney Morning Herald",
            "title": "Home And A Wage",
            "url": null,
            "timestamp": "2001-03-03",
            "text": "In the main, the women workers have made the concessions. ..."
        },
        {
            "id": "11915",
            "publisher": " The Age ",
            "title": "\nFoster Love & Care\n",
            "url": null,
            "timestamp": "1992-11-25",
            "text": "Now 19\nand working as a housekeeper at Beltara, a secure welfare institution\nfor youths, she says until she spent six months with a terrific foster\nfamily she had thought no families were happy. ..."
        },
        {
            "id": "19019",
            "publisher": "Courier Mail",
            "title": "\nWomen just can't win.\n",
            "url": null,
            "timestamp": "1999-12-27",
            "text": "Earlier this year Senator Jocelyn Newman's Department of Social Security gave substantial funding to the vociferously anti-women Lone Fathers' Association - a group that sees the Family Law Act as set up to rob them of their rights - while ending a long-t ..."
        },
        {
            "id": "10920",
            "publisher": "The Sydney Morning Herald",
            "title": "How a fair society is winning voters",
            "url": null,
            "timestamp": "2014-06-21",
            "text": "If the latter is the case, why is none of the revenue being funnelled back to the bottom line in the short term? ..."
        },
        {
            "id": "15045",
            "publisher": "The Age",
            "title": "Who Cares?",
            "url": null,
            "timestamp": "1999-11-03",
            "text": "The study found that the large number of people leaving day-care centres, or cutting back their child's hours, had caused community child-care centres to close at record rates in the past two years- especially in Australia's poorest suburbs and towns. ..."
        },
        {
            "id": "23819",
            "publisher": " Sydney Morning Herald ",
            "title": "\nUNHAPPILY EVER AFTER\n",
            "url": null,
            "timestamp": "1997-11-08",
            "text": "UNHAPPILY EVER AFTER\n \nWhy a bad marriage may be better for your children than a good\ndivorce. STAYING together for the sake of the kids. It's such an outdated\nnotion. ..."
        },
        {
            "id": "9661",
            "publisher": "The Australian",
            "title": "\nIt'll cost to fix flaws in welfare.\n",
            "url": null,
            "timestamp": "2000-03-29",
            "text": "With no end in sight to the trends it highlights, the present welfare system is unsustainable in the long run: an increasing proportion of the population would become wholly or partially reliant on government benefits, which would be paid for by a decreas ..."
        },
        {
            "id": "22258",
            "publisher": "Herald-Sun",
            "title": "\nWORKPLACE UPDATE.\n",
            "url": null,
            "timestamp": "1998-01-31",
            "text": "Farm jobs grow AN agricultural academic has disputed claims farming has only parched employment opportunities. ..."
        },
        {
            "id": "10617",
            "publisher": " Sydney Morning Herald ",
            "title": "\nPoorer Families Get Some Tax Relief\n",
            "url": null,
            "timestamp": "1996-08-21",
            "text": "Higher child-care charges at community day-care centres will be a great\ndeal more than $3.85 as a result of the abolition of operational\nsubsidies. Other Budget changes will also affect family life detrimentally. ..."
        },
        {
            "id": "27643",
            "publisher": " Sydney Morning Herald ",
            "title": "\nBARE TRUTHS ABOUT OUR INVISIBLE SCANDAL\n",
            "url": null,
            "timestamp": "1992-06-09",
            "text": "But the Government has failed to maintain funding, and the Coalition\nwants  virtually to dismantle public housing and replace it with more\nreliance on the private market. ..."
        },
        {
            "id": "13049",
            "publisher": "Sydney Morning Herald",
            "title": "Catholics Hit Out At `Mickey Mouse' Review",
            "url": null,
            "timestamp": "1999-12-20",
            "text": "The NSW St Vincent de Paul criticises the Minister for Family and Community Services, Senator Newman, for her suggestion that thousands of Australians preferred to live on welfare rather than work. ..."
        },
        {
            "id": "26904",
            "publisher": "Sydney Morning Herald",
            "title": "Welfare Reform Requires Compassion, Not A Stick",
            "url": null,
            "timestamp": "1999-10-02",
            "text": "Welfare Reform Requires Compassion, Not A Stick Insensitive welfare reform risks making the lives of some of our poor even worse. JOCELYN Newman is right when she says that welfare reform may cost - not save - the Government money. ..."
        },
        {
            "id": "19509",
            "publisher": "The Australian",
            "title": "\nDouble-parent-no-income our new class.\n",
            "url": null,
            "timestamp": "1999-07-15",
            "text": "It notes that the impact of the trends on rates of child poverty have been lessened considerably by the growth in government income-support. ..."
        },
        {
            "id": "24185",
            "publisher": "The Sydney Morning Herald",
            "title": "Taking the scalpel to DOCS",
            "url": null,
            "timestamp": "2008-07-19",
            "text": "She sought help from DOCS because she was depressed and felt she was not able to cope. She was told her circumstances were not serious enough to warrant a response. ..."
        },
        {
            "id": "5023",
            "publisher": "The Australian Financial Review",
            "title": "COALITION WINNING FEMALE VOTERS WITH REBATE PLAN",
            "url": null,
            "timestamp": "1989-10-17",
            "text": "Like any political document, it has not pleased everyone. And the diverse collection of women's groups around Australia are no exception. ..."
        },
        {
            "id": "25950",
            "publisher": "The Australian",
            "title": "\nDOWNWARD ENVY / WHY MIDDLE AUSTRALIA HATES THE POOR.\n",
            "url": null,
            "timestamp": "1996-11-02",
            "text": "The family may be in public housing but, if renting on the private market, is entitled to rent assistance of up to $87 a fortnight, depending on the rental cost. The basic wage in the Metal Workers Award is $9.10 an hour or $345.80 for a 38-hour week. ..."
        },
        {
            "id": "7244",
            "publisher": " Sydney Morning Herald ",
            "title": "\nGIVE US A BREAK\n",
            "url": null,
            "timestamp": "1997-05-19",
            "text": "Soon, in some areas, child care\nplaces outnumbered children. Oversupply of centres did not necessarily mean an improvement in\nquality. Competition meant centres cut costs, mostly by reducing staff\nnumbers, which resulted in a drastic affect on quality. ..."
        },
        {
            "id": "9694",
            "publisher": "Daily Telegraph",
            "title": "\nLABOR'S DEMAND ON GST BACKFIRES.\n",
            "url": null,
            "timestamp": "1998-11-12",
            "text": "The major parties stumbled into confusion as bartering began over the timing of the tax legislation and the crucial question of a Senate inquiry into its impact. ..."
        },
        {
            "id": "30890",
            "publisher": " Sydney Morning Herald ",
            "title": "\nLOW-INCOME TENANTS TO GET HELP FIRST\n",
            "url": null,
            "timestamp": "1992-08-19",
            "text": "The threshold for rent assistance will also be lifted from $50 a\nfortnight  to between $60 and $120 a fortnight depending upon family\nsize. ..."
        },
        {
            "id": "4001",
            "publisher": " The West Australian ",
            "title": "\nHow Reality Met Hopes Of Families\n",
            "url": null,
            "timestamp": "1997-05-14",
            "text": "The Nortjes were happy that no new taxes had been introduced,\nparticularly sales tax which they had seen escalate in South Africa. \"Once sales taxes start to rise, they are very hard to stop and the\ncustomer is the one who has to pay,\" Mr Nortje said. ..."
        },
        {
            "id": "32263",
            "publisher": "The Sydney Morning Herald - Online",
            "title": "Liberal Party lost the trust of Australian women long before Morrison",
            "url": null,
            "timestamp": "2022-06-08",
            "text": "By 1981, Mahlab had spent a decade in the trenches with the Women's Electoral Lobby, fighting for family law reform and abortion rights, and taking part in the Victorian Hamer government's inquiry into the status of women. ..."
        },
        {
            "id": "23791",
            "publisher": " Sydney Morning Herald ",
            "title": "\nParents Rescued From The Brink Of Disaster\n",
            "url": null,
            "timestamp": "1995-09-27",
            "text": "The girls, then six and eight, kept running away\nand told DOCS workers that their mother hit them all the time. \"I was following in the footsteps of my mum,\" said Bronwyn, a loud and\ncheerful woman. ..."
        },
        {
            "id": "23890",
            "publisher": " Sydney Morning Herald ",
            "title": "\nUNHAPPILY EVER AFTER\n",
            "url": null,
            "timestamp": "1997-11-08",
            "text": "The true picture has turned out to be far more complex. Yes, it's\ncertainly true most people repartner after divorce. Almost half the\nchildren whose parents  divorce have a stepfather within six years. ..."
        },
        {
            "id": "22274",
            "publisher": " The Age ",
            "title": "\nParents Seeking Care For Children To Benefit\n",
            "url": null,
            "timestamp": "1992-08-19",
            "text": "Working parents using long day child-care have been given a\n$5.50-a-week boost to fee relief, taking the maximum subsidy available\nper child to $93 a week. ..."
        },
        {
            "id": "18756",
            "publisher": " The Age ",
            "title": "\nSocial Conundrum: Is A Bad Marriage Better Than A Good Divorce?\n",
            "url": null,
            "timestamp": "1997-11-08",
            "text": "But after the divorce, children often become the prime focus of their\nparents, caught up in bitter arguments about arrangements for their\ncare. The low-conflict good divorce seems a rarity - at least according to\nthe overseas research. ..."
        },
        {
            "id": "8275",
            "publisher": "The Australian Financial Review",
            "title": "Tax reform offers our place in the sun",
            "url": null,
            "timestamp": "2003-11-10",
            "text": "The implications for welfare are enormous. Basically, it means a big welfare state is no longer needed. ..."
        },
        {
            "id": "11510",
            "publisher": " The Age ",
            "title": "\n90% Tax Hits Sole Parents, Says Lobby Group\n",
            "url": null,
            "timestamp": "1991-04-26",
            "text": "The council estimated that the number of sole parents living in\npoverty had neared 100,000 because of the recession. In the 1982-83\nrecession, the number of  sole parents living in poverty had jumped by\n20 per cent. ..."
        },
        {
            "id": "1075",
            "publisher": "Hobart Mercury",
            "title": "\nMP gags welfare inquiry.\n",
            "url": null,
            "timestamp": "1999-11-12",
            "text": "MP gags welfare inquiry. FAMILY and Community Services Minister Jocelyn Newman has gagged senior officials from revealing details of her controversial welfare reform paper to a Senate inquiry today. ..."
        },
        {
            "id": "20728",
            "publisher": "The Sydney Morning Herald",
            "title": "Living off the public teat",
            "url": null,
            "timestamp": "2009-02-21",
            "text": "The reduced demand for unskilled labour has, then, been a major factor driving the overall increase in welfare dependency in this country over the past 30 years or so. But it is not the only one. ..."
        },
        {
            "id": "13894",
            "publisher": " Sydney Morning Herald ",
            "title": "\n200,000 WILL BE HIT BY CUTS IN RENT SUBSIDIES\n",
            "url": null,
            "timestamp": "1986-12-26",
            "text": "The maximum rate of rent assistance payable is $15 a week for\npensioners, including supporting parents and sickness beneficiaries, and\n$10 a week for people who have been receiving unemployment and special\nbenefit for more than six months. ..."
        },
        {
            "id": "29159",
            "publisher": " The Age ",
            "title": "\nA Time When Income Inequality Doesn't Really Matter\n",
            "url": null,
            "timestamp": "1995-04-21",
            "text": "On this foundation, many academic  careers and\nmany high salaries were built, as well as a permanently dissatisfied\nwelfare lobby. ..."
        },
        {
            "id": "858",
            "publisher": "Herald-Sun",
            "title": "\nMothers left out in the cold.\n",
            "url": null,
            "timestamp": "1999-12-14",
            "text": "About four community childcare centres and three private ones remain but the the average cost of childcare had soared 10 per cent to $148 a week in the past two years. ..."
        },
        {
            "id": "16607",
            "publisher": "Sydney Morning Herald",
            "title": "Kids Pay Ground",
            "url": null,
            "timestamp": "1999-09-08",
            "text": "VACATION CARE\n\nPrimary school children may be cared for during school holidays. Cost: About $20 a day, possibly more, depending on types of excursions. Child-care assistance: Yes. ..."
        },
        {
            "id": "28946",
            "publisher": " The Age ",
            "title": "\nHeartfelt Search For Ties That Bind Across Lost Years\n",
            "url": null,
            "timestamp": "1993-06-15",
            "text": "``I would like to\nthank Brenda for my family, and for getting all the families here\ntogether,'' she said. Ms Berry's brother Rob Baker, 42, had come from Geelong with his wife\nJenny and baby son Shane. ..."
        },
        {
            "id": "995",
            "publisher": "Herald-Sun",
            "title": "\nSCHOOL FOR PARENTS.\n",
            "url": null,
            "timestamp": "2000-04-03",
            "text": "Senator Newman said yesterday welfare and social policy was the government's top priority. ..."
        },
        {
            "id": "6743",
            "publisher": "Sydney Morning Herald",
            "title": "Credit Where It's Due",
            "url": null,
            "timestamp": "1999-03-10",
            "text": "Economists - and the public - worry that some people on welfare don't want to work because the extra money they'd get wouldn't be enough to make up for the extra effort. ..."
        },
        {
            "id": "24347",
            "publisher": "The Australian Financial Review",
            "title": "Budget has its work cut out",
            "url": null,
            "timestamp": "2005-05-09",
            "text": "For middle and high-income earners the tax system has become a giant loop, extracting money at one point but dribbling it back at another. This absurd arrangement can be eliminated with relatively little damage to revenue. ..."
        },
        {
            "id": "1479",
            "publisher": "Sydney Morning Herald",
            "title": "Double Or Nothing",
            "url": null,
            "timestamp": "1999-12-02",
            "text": "Couples who choose to cohabit are also likely to hold attitudes that make them more prone to divorce. Glezer found that the couples most likely to live together usually have fewer traditional values and place more emphasis on personal autonomy. ..."
        },
        {
            "id": "24693",
            "publisher": "The Australian Financial Review",
            "title": "Childcare is a middle-class perk",
            "url": null,
            "timestamp": "2015-07-03",
            "text": "Over the past decade or so, subsidies for childcare have grown continuously and rapidly to the point where they now pose a real threat to long-term budget sustainability. ..."
        },
        {
            "id": "2701",
            "publisher": "The Australian Financial Review",
            "title": "PUBLIC OR PRIVATE, NO MAGIC WAND WILL END THE PROBLEM OF CHILD CARE",
            "url": null,
            "timestamp": "1988-07-13",
            "text": "PUBLIC OR PRIVATE, NO MAGIC WAND WILL END THE PROBLEM OF CHILD CARE ECONOMIC PERSPECTIVE\n\nPERSONALLY, I reckon that the biggest problem with kids is parents. Children, of course, are not free to choose. ..."
        },
        {
            "id": "14848",
            "publisher": "The Age",
            "title": "Howard's Tax Pack Is Still A Poverty Trap",
            "url": null,
            "timestamp": "1999-02-23",
            "text": "By redirecting family benefits to the needy, Labor reduced the rate of child poverty by a third between 1982 and 1995, according to the National Centre of Social and Economic Modelling (NATSEM). But we are now coming to realise that it has a downside. ..."
        },
        {
            "id": "30238",
            "publisher": "Adelaide Advertiser",
            "title": "\nChildren $24 worse off than in 1982.\n",
            "url": null,
            "timestamp": "1999-06-07",
            "text": "\"In 1982, almost half of all dependent children lived in couple families where only one parent worked,\" she said. \"But by the mid-1990s, this proportion had fallen to 31 per cent.\" ..."
        },
        {
            "id": "17406",
            "publisher": "The Sydney Morning Herald",
            "title": "Letters",
            "url": null,
            "timestamp": "2011-05-07",
            "text": "It comes down to corporations jumping from one scenario to the other, before slow-moving governments have the nous and legislation to set new taxes for new situations. Inevitable. Donald Hawes Blayney (ACT). ..."
        },
        {
            "id": "20320",
            "publisher": " Sydney Morning Herald ",
            "title": "\nGAP GROWING? KEATING SAYS NO\n",
            "url": null,
            "timestamp": "1992-10-14",
            "text": "A wealth tax has been repeatedly pushed off the political agenda for\nmuch the same reasons. Yet most Western countries have an annual tax on\nwealth in some form. ..."
        },
        {
            "id": "26605",
            "publisher": "Daily Telegraph",
            "title": "\nDIVORCE NOT SO BAD FOR CHILDREN.\n",
            "url": null,
            "timestamp": "1998-06-25",
            "text": "Sociologists yesterday dismissed the report as absurd and bizarre. The conclusions were drawn by two Australian researchers who examined 200 British studies on the impact of divorce. ..."
        },
        {
            "id": "18600",
            "publisher": " The Age ",
            "title": "\nJobs Help To Boost Incomes On Welfare\n",
            "url": null,
            "timestamp": "1996-01-03",
            "text": "The Government had restructured the income test for unemployment\npayments, including an earnings credit for people doing irregular\npart-time work, he said. ..."
        },
        {
            "id": "12748",
            "publisher": "The Australian",
            "title": "\nLETTERS - No one is passing judgment on single parents.\n",
            "url": null,
            "timestamp": "1997-12-15",
            "text": "A group of very determined, creative and intelligent young women are challenging those stereotypes. ..."
        },
        {
            "id": "28322",
            "publisher": "The Australian Financial Review",
            "title": "BEHIND THE MYTH OF WOMEN'S EQUALITY",
            "url": null,
            "timestamp": "1991-12-20",
            "text": "The indications are that as they are becoming unemployed they are retreating into the homes, unable to find other part-time work. Consequently they are unlikely to rock the boat. ..."
        },
        {
            "id": "27612",
            "publisher": " Sydney Morning Herald ",
            "title": "\nHOWE DOWNPLAYS SPENDING CUTS\n",
            "url": null,
            "timestamp": "1988-05-02",
            "text": "What we're going to do to further improve the performance of our\nindustries. It's going to go to a further stage in the process of tax\nreform. \"It's going to deal only partially with questions of expenditure\nrestraint. ..."
        },
        {
            "id": "21110",
            "publisher": "The Australian Financial Review",
            "title": "CHILDCARE SPENDING BOOSTED BY $129M AND FEE RELIEF UP",
            "url": null,
            "timestamp": "1991-08-21",
            "text": "This change will entitle most lower class income earners to around $85 a week child care fee relief in occasional child care centres, compared to the maximum $55 a week entitlement now. ..."
        },
        {
            "id": "30251",
            "publisher": "Sydney Morning Herald",
            "title": "Cabinet Approves Reining In Welfare",
            "url": null,
            "timestamp": "1999-11-10",
            "text": "Sole parent groups argue that the present training schemes are oversubscribed, especially since cuts. But Senator Newman says there is scope for more assistance to help parents back into the workforce. ..."
        },
        {
            "id": "11747",
            "publisher": " The Age ",
            "title": "\nLabour's First Budget Streamlines Welfare System\n",
            "url": null,
            "timestamp": "1998-03-19",
            "text": "It will be a\nwhile before the effect of the changes - if they work - shows up in\nunemployment figures. ..."
        },
        {
            "id": "30881",
            "publisher": " Sydney Morning Herald ",
            "title": "\nLOW-INCOME TENANTS TO GET HELP FIRST\n",
            "url": null,
            "timestamp": "1992-08-19",
            "text": "States will be able to use the funding to either upgrade existing\npublic housing stock or construct new buildings in areas of high\nunemployment, with hopes of 1,600 jobs to be created. ..."
        },
        {
            "id": "9292",
            "publisher": "Herald-Sun",
            "title": "\nA MESSAGE TO THE YOUNG ONES.\n",
            "url": null,
            "timestamp": "1998-02-10",
            "text": "Welfare lobbyists are already slamming the idea. Many single mothers will strongly object, citing the fact they are a poverty-stricken group already. What they need is more help, not more pressure, many would say. ..."
        },
        {
            "id": "22211",
            "publisher": " The Age ",
            "title": "\nTax: Does Labor Have A Credible Alternative?\n",
            "url": null,
            "timestamp": "1998-08-22",
            "text": "Without a large\nbroadening of the tax base, notably by bringing the services sector into\nplay, the burden on PAYE taxpayers will increase exponentially. As business leaders have warned, this may be a recipe for a tax\nrevolt. ..."
        },
        {
            "id": "11371",
            "publisher": "The Age",
            "title": "Children's Poverty To Worsen",
            "url": null,
            "timestamp": "1999-07-15",
            "text": "Professor Gregory said that last year 18per cent of dependent children lived in a family in which neither parent was employed. This compared to just 11per cent 20 years ago. And the trend was expected to continue. ..."
        },
        {
            "id": "22533",
            "publisher": "The Australian",
            "title": "\nMother LOAD.\n",
            "url": null,
            "timestamp": "1997-10-04",
            "text": "Mother LOAD. For many mothers, there are only token financial benefits in returning to work, a new study has found. After decades of feminist-inspired reform, why are mothers still so undervalued? ..."
        },
        {
            "id": "23830",
            "publisher": " Sydney Morning Herald ",
            "title": "\nUNHAPPILY EVER AFTER\n",
            "url": null,
            "timestamp": "1997-11-08",
            "text": "The Australian findings confirmed\noverseas trends showing children of divorce are twice as likely to\nexperience problems as those whose parents stay in a reasonably\nsatisfactory intact marriage. ..."
        },
        {
            "id": "25614",
            "publisher": " The Age ",
            "title": "\nEncouraging Women To Explore Job Options\n",
            "url": null,
            "timestamp": "1995-08-07",
            "text": "``It can be such a shock to a woman. One minute she is a wife and\nmother, the  next she is just a mother, and that usually means a\ndrastically reduced income and lifestyle. ..."
        },
        {
            "id": "4026",
            "publisher": " The West Australian ",
            "title": "\nHow Reality Met Hopes Of Families\n",
            "url": null,
            "timestamp": "1997-05-14",
            "text": "He said much of that depended on changing\nfringe benefit tax laws which made fly-in, fly-out operations more cost\neffective for mining and petroleum companies than building local\ncommunities. ..."
        },
        {
            "id": "5242",
            "publisher": "The Australian Financial Review",
            "title": "Dismantling the welfare state",
            "url": null,
            "timestamp": "1996-10-25",
            "text": "Society has set limits on the amount it is willing to pay in taxes and the amount it is willing for governments to spend on social welfare. The resentment the welfare state bred made it financially unsustainable. ..."
        },
        {
            "id": "7463",
            "publisher": " Sydney Morning Herald ",
            "title": "\nFOR THE KIDS, SEPARATED PARENTS CAN MEAN RICHES TO RAGS\n",
            "url": null,
            "timestamp": "1990-06-01",
            "text": "Also, the wives of the high earners were less likely than the others\nto have found a new partner. Less than one-third had re-partnered six\nto eight years after separation. ..."
        },
        {
            "id": "23656",
            "publisher": " Sydney Morning Herald ",
            "title": "\nBreak-ups `the Main Cause Of Poverty'\n",
            "url": null,
            "timestamp": "1997-09-22",
            "text": "Lone parents made up 16.3 per cent of all families with dependent\nchildren in  1991; 17.7 per cent in 1994 and 19.4 per cent in 1996. Most\nof these households  were headed by women. ..."
        },
        {
            "id": "15758",
            "publisher": "Courier Mail",
            "title": "\nSlugging victims a second time.\n",
            "url": null,
            "timestamp": "1999-04-10",
            "text": "Almost without exception that particular class of person is dependent on social security to exist. ..."
        },
        {
            "id": "25507",
            "publisher": " The Age ",
            "title": "\nWelfare Feels The Pain\n",
            "url": null,
            "timestamp": "1992-12-24",
            "text": "However, since kindergartens\ncater mainly for the children whose mothers can afford to stay home,\nwhile the  cut-back day nurseries take many children of sole parents and\nlow-income families where both  parents work, this is unlikely to\nreassure critics. ..."
        },
        {
            "id": "9972",
            "publisher": "Sydney Morning Herald",
            "title": "The Politics Of Appeasing The Poor",
            "url": null,
            "timestamp": "2000-11-17",
            "text": "Of direct relevance to the decisions the Government is now taking on McClure is NATSEM's finding that poverty ``is now a phenomenon that primarily affects those of working age''. ..."
        },
        {
            "id": "8006",
            "publisher": "The Sydney Morning Herald",
            "title": "Taking sides over shacking up",
            "url": null,
            "timestamp": "2011-08-20",
            "text": "But 11 per cent lived with biological parents who were cohabiting while 9 per cent lived with a sole parent who had divorced or separated. ..."
        },
        {
            "id": "17135",
            "publisher": " Sydney Morning Herald ",
            "title": "\nHAWKE NEEDS MORE OF A SWAN SONG\n",
            "url": null,
            "timestamp": "1989-01-28",
            "text": "A new notion had to be\nexplained to the press and the public. ..."
        },
        {
            "id": "21810",
            "publisher": " The Age ",
            "title": "\nCommunity Groups Call For Talks On Policies\n",
            "url": null,
            "timestamp": "1992-11-13",
            "text": "The spokesman said Bishop Challen appeared to be unaware of the 80\namendments  that the Government had made to its bills. ..."
        },
        {
            "id": "520",
            "publisher": " The Age ",
            "title": "\nSearching For The Lost Families\n",
            "url": null,
            "timestamp": "1992-09-12",
            "text": "This inspired Ms Fitzgerald to search for the families of other\nresidents, and other staff started referring more people to her. ..."
        }
    ],
    "lines": [
        {
            "id": "0",
            "links": [
                {
                    "source": "0_2",
                    "target": "1_2"
                },
                {
                    "source": "1_2",
                    "target": "2_2"
                },
                {
                    "source": "2_2",
                    "target": "3_2"
                },
                {
                    "source": "3_2",
                    "target": "4_2"
                },
                {
                    "source": "4_2",
                    "target": "5_2"
                }
            ],
            "weight": 1.0,
            "line_label": "poverty, cent"
        },
        {
            "id": "1",
            "links": [
                {
                    "source": "0_4",
                    "target": "1_4"
                },
                {
                    "source": "1_4",
                    "target": "2_4"
                },
                {
                    "source": "2_4",
                    "target": "3_4"
                },
                {
                    "source": "3_4",
                    "target": "4_4"
                },
                {
                    "source": "4_4",
                    "target": "5_4"
                }
            ],
            "weight": 0.6721299250562894,
            "line_label": "women"
        },
        {
            "id": "2",
            "links": [
                {
                    "source": "0_9",
                    "target": "1_9"
                },
                {
                    "source": "1_9",
                    "target": "2_9"
                },
                {
                    "source": "2_9",
                    "target": "3_9"
                },
                {
                    "source": "3_9",
                    "target": "4_9"
                },
                {
                    "source": "4_9",
                    "target": "5_9"
                }
            ],
            "weight": 0.45990195244455623,
            "line_label": "tax"
        },
        {
            "id": "3",
            "links": [
                {
                    "source": "0_1",
                    "target": "1_1"
                },
                {
                    "source": "1_1",
                    "target": "2_1"
                },
                {
                    "source": "2_1",
                    "target": "3_9"
                },
                {
                    "source": "3_9",
                    "target": "4_9"
                },
                {
                    "source": "4_9",
                    "target": "5_9"
                }
            ],
            "weight": 0.39862028575669795,
            "line_label": "housing, tax"
        },
        {
            "id": "4",
            "links": [
                {
                    "source": "0_7",
                    "target": "1_7"
                },
                {
                    "source": "1_7",
                    "target": "2_7"
                },
                {
                    "source": "2_7",
                    "target": "3_7"
                },
                {
                    "source": "3_7",
                    "target": "4_7"
                },
                {
                    "source": "4_7",
                    "target": "5_7"
                }
            ],
            "weight": 0.2519796069333232,
            "line_label": "rooney, welfare"
        },
        {
            "id": "5",
            "links": [
                {
                    "source": "0_5",
                    "target": "1_5"
                },
                {
                    "source": "1_5",
                    "target": "2_5"
                },
                {
                    "source": "2_5",
                    "target": "3_4"
                },
                {
                    "source": "3_4",
                    "target": "4_4"
                },
                {
                    "source": "4_4",
                    "target": "5_4"
                }
            ],
            "weight": 0.24430147615510756,
            "line_label": "unemployed, sex"
        },
        {
            "id": "6",
            "links": [
                {
                    "source": "0_8",
                    "target": "1_8"
                },
                {
                    "source": "1_8",
                    "target": "2_8"
                },
                {
                    "source": "2_8",
                    "target": "3_8"
                },
                {
                    "source": "3_8",
                    "target": "4_8"
                },
                {
                    "source": "4_8",
                    "target": "5_8"
                }
            ],
            "weight": 0.20112621904703876,
            "line_label": "care, 2001"
        },
        {
            "id": "7",
            "links": [
                {
                    "source": "0_3",
                    "target": "1_3"
                },
                {
                    "source": "1_3",
                    "target": "2_3"
                },
                {
                    "source": "2_3",
                    "target": "3_3"
                },
                {
                    "source": "3_3",
                    "target": "4_3"
                },
                {
                    "source": "4_3",
                    "target": "5_3"
                }
            ],
            "weight": 0.12842388179956266,
            "line_label": "divorce, marriage"
        },
        {
            "id": "8",
            "links": [
                {
                    "source": "0_6",
                    "target": "1_6"
                },
                {
                    "source": "1_6",
                    "target": "2_6"
                },
                {
                    "source": "2_6",
                    "target": "3_6"
                },
                {
                    "source": "3_6",
                    "target": "4_6"
                },
                {
                    "source": "4_6",
                    "target": "5_6"
                }
            ],
            "weight": 0.015202867387784313,
            "line_label": "security, social"
        },
        {
            "id": "9",
            "links": [
                {
                    "source": "0_0",
                    "target": "1_0"
                },
                {
                    "source": "1_0",
                    "target": "2_0"
                },
                {
                    "source": "2_0",
                    "target": "3_0"
                },
                {
                    "source": "3_0",
                    "target": "4_0"
                },
                {
                    "source": "4_0",
                    "target": "5_7"
                }
            ],
            "weight": 0.0,
            "line_label": "newman"
        }
    ]
}